{
  "fields": [
    {
      "metadata": {},
      "name": "id",
      "nullable": true,
      "type": "long"
    },
    {
      "metadata": {},
      "name": "user",
      "nullable": true,
      "type": {
        "fields": [
          {
            "metadata": {},
            "name": "id",
            "nullable": true,
            "type": "long"
          },
          {
            "metadata": {},
            "name": "login",
            "nullable": true,
            "type": "string"
          }
        ],
        "type": "struct"
      }
    },
    {
      "metadata": {},
      "name": "created_at",
      "nullable": true,
      "type": "string"
    },
    {
      "metadata": {},
      "name": "path",
      "nullable": true,
      "type": "string"
    },
    {
      "metadata": {},
      "name": "position",
      "nullable": true,
      "type": "integer"
    },
    {
      "metadata": {},
      "name": "commit_id",
      "nullable": true,
      "type": "string"
    }
  ],
  "type": "struct"
}
